irrigation_caddy/__init__.py
irrigation_caddy/irrigation_caddy.py
irrigation_caddy-0.0.4.dist-info/LICENSE
irrigation_caddy-0.0.4.dist-info/METADATA
irrigation_caddy-0.0.4.dist-info/WHEEL
irrigation_caddy-0.0.4.dist-info/top_level.txt
irrigation_caddy-0.0.4.dist-info/RECORD
